ExMenteDataAnalysis/__init__.py
ExMenteDataAnalysis/app.py
ExMenteDataAnalysis-1.1.0.dist-info/METADATA
ExMenteDataAnalysis-1.1.0.dist-info/WHEEL
ExMenteDataAnalysis-1.1.0.dist-info/top_level.txt
ExMenteDataAnalysis-1.1.0.dist-info/RECORD
