Metadata-Version: 2.1
Name: ExMenteDataAnalysis
Version: 1.1.0
Summary: Ex Mente Junior Developer Assignment
Author: Nicholas Holtzhausen
Author-email: nholtzhausen54@gmail.com
Keywords: python,data,analysis
Classifier: Development Status :: 1 - Planning
Classifier: Intended Audience :: Developers
Classifier: Programming Language :: Python :: 3
Classifier: Operating System :: Unix
Classifier: Operating System :: MacOS :: MacOS X
Classifier: Operating System :: Microsoft :: Windows
Requires-Dist: pandas
Requires-Dist: matplotlib
